pyramid_log/__init__.py
pyramid_log/_compat.py
pyramid_log/test_compat.py
pyramid_log/tests.py
pyramid_log-1.0.1.dist-info/LICENSE
pyramid_log-1.0.1.dist-info/METADATA
pyramid_log-1.0.1.dist-info/WHEEL
pyramid_log-1.0.1.dist-info/top_level.txt
pyramid_log-1.0.1.dist-info/RECORD
